<?xml version="1.0" encoding="utf-8" ?>
<Pages>
  <MainMenu>报表统计</MainMenu>
  <SubMenu>会员卡单卡充值消费分析</SubMenu>
  <Menu>会员卡单卡充值消费分析</Menu>
  <Title>会员卡单卡充值消费分析</Title>
  <GoBack>会员卡单卡充值消费分析</GoBack>
  <!--优惠券列表-条件-->
  <stime_where>开始时间：</stime_where>
  <etime_where>结束时间：</etime_where>
  <cardcode_where>会员卡号：</cardcode_where>
  <birthday_where>生日：</birthday_where>
  <ctype_where>会员卡类型：</ctype_where>
  <cracode_where>会员卡等级：</cracode_where>
  <!--优惠券列表-Grid-->
  <cardcode_list>会员卡号</cardcode_list>
  <name_list>姓名</name_list>
  <mobile_list>手机号</mobile_list>
  <ctypename_list>会员卡类型</ctypename_list>
  <cracode_list>会员卡等级</cracode_list>
  <chargenum_list>充值次数</chargenum_list>
  <chargemoney_list>累计充值金额</chargemoney_list>
  <salenum_list>消费次数</salenum_list>
  <salemoney_list>累计消费金额</salemoney_list>
  <balance_list>当前卡余额</balance_list>
  <birthday_list>生日</birthday_list>
  <!--优惠券列表-条件-->
  <!--优惠券-新增-->
  <tab1>基本信息</tab1>
</Pages>